perfect.py
perfect_html-0.0.6.dist-info/DESCRIPTION.rst
perfect_html-0.0.6.dist-info/METADATA
perfect_html-0.0.6.dist-info/RECORD
perfect_html-0.0.6.dist-info/WHEEL
perfect_html-0.0.6.dist-info/entry_points.txt
perfect_html-0.0.6.dist-info/metadata.json
perfect_html-0.0.6.dist-info/top_level.txt
